vinyl/__init__.py
vinyl/cli/__init__.py
vinyl/cli/_project_scaffolding/README.md
vinyl/cli/_project_scaffolding/__project_name__/__init__.py
vinyl/cli/_project_scaffolding/__project_name__/data/holidays_events.csv
vinyl/cli/_project_scaffolding/__project_name__/data/store_num_transactions.csv
vinyl/cli/_project_scaffolding/__project_name__/data/stores.csv
vinyl/cli/_project_scaffolding/__project_name__/models/__init__.py
vinyl/cli/_project_scaffolding/__project_name__/resources.py
vinyl/cli/_project_scaffolding/__project_name__/sources/__init__.py
vinyl/cli/_project_scaffolding/pyproject.toml
vinyl/cli/main.py
vinyl/cli/preview.py
vinyl/cli/project.py
vinyl/cli/sources.py
vinyl/connect.py
vinyl/docs/charts.ipynb
vinyl/docs/metrics.ipynb
vinyl/infra/__init__.py
vinyl/infra/pg_proxy/README.md
vinyl/infra/pg_proxy/__init__.py
vinyl/infra/pg_proxy/backends/__init__.py
vinyl/infra/pg_proxy/backends/duckdb.py
vinyl/infra/pg_proxy/bv_dialects.py
vinyl/infra/pg_proxy/core.py
vinyl/infra/pg_proxy/postgres.py
vinyl/infra/pg_proxy/rewrite.py
vinyl/infra/pg_proxy/server.py
vinyl/lib/__init__.py
vinyl/lib/asset.py
vinyl/lib/chart.py
vinyl/lib/column.py
vinyl/lib/connect.py
vinyl/lib/constants.py
vinyl/lib/definitions.py
vinyl/lib/enums.py
vinyl/lib/erd.py
vinyl/lib/expressions.py
vinyl/lib/field.py
vinyl/lib/graph.py
vinyl/lib/metric.py
vinyl/lib/operators.py
vinyl/lib/project.py
vinyl/lib/schema.py
vinyl/lib/settings.py
vinyl/lib/source.py
vinyl/lib/sources/source.py
vinyl/lib/table.py
vinyl/lib/table_methods.py
vinyl/lib/temporal.py
vinyl/lib/utils/ast.py
vinyl/lib/utils/context.py
vinyl/lib/utils/files.py
vinyl/lib/utils/functions.py
vinyl/lib/utils/graph.py
vinyl/lib/utils/graphics.py
vinyl/lib/utils/obj.py
vinyl/lib/utils/pkg.py
vinyl/lib/utils/polyglot.py
vinyl/lib/utils/text.py
vinyl_core-0.0.8.dist-info/METADATA
vinyl_core-0.0.8.dist-info/WHEEL
vinyl_core-0.0.8.dist-info/entry_points.txt
vinyl_core-0.0.8.dist-info/RECORD
